defopt-stubs/__init__.pyi
defopt-stubs/py.typed
defopt_stubs-0.1.0rc2.dist-info/licenses/LICENSE
defopt_stubs-0.1.0rc2.dist-info/METADATA
defopt_stubs-0.1.0rc2.dist-info/WHEEL
defopt_stubs-0.1.0rc2.dist-info/top_level.txt
defopt_stubs-0.1.0rc2.dist-info/RECORD
