Metadata-Version: 2.4
Name: defopt-stubs
Version: 0.1.0rc2
Summary: Typing stubs for the defopt package
Author-email: Daniel Pope <mauve@mauveweb.co.uk>
License: MIT
Classifier: Programming Language :: Python :: 3
Classifier: License :: OSI Approved :: MIT License
Classifier: Typing :: Stubs Only
Requires-Python: >=3.8
License-File: LICENSE
Dynamic: license-file
